pymake3/__init__.py
pymake3/report.py
pymake3/cli/__init__.py
pymake3/cli/info.py
pymake3/cli/main.py
pymake3/cli/options.py
pymake3/core/__init__.py
pymake3/core/decorators.py
pymake3/core/exceptions.py
pymake3/core/makeconf.py
pymake3/core/maker.py
pymake3/core/target.py
pymake3/makeutils/__init__.py
pymake3/makeutils/fs.py
pymake3/makeutils/proc.py
pymake3/template/__init__.py
pymake3/template/c/__init__.py
pymake3/template/c/cl.py
pymake3/template/csharp/__init__.py
pymake3/template/csharp/csc.py
pymake3/template/latex/__init__.py
pymake3/template/latex/pdflatex.py
pymake3/template/util/__init__.py
pymake3/template/util/fswatcher.py
pymake3/utils/__init__.py
pymake3/utils/color.py
pymake3-0.0.2.dist-info/DESCRIPTION.rst
pymake3-0.0.2.dist-info/METADATA
pymake3-0.0.2.dist-info/RECORD
pymake3-0.0.2.dist-info/WHEEL
pymake3-0.0.2.dist-info/metadata.json
pymake3-0.0.2.dist-info/top_level.txt
